the0/__init__.py
the0/query.py
the0/state.py
the0_sdk-0.3.1.dist-info/licenses/LICENSE
the0_sdk-0.3.1.dist-info/METADATA
the0_sdk-0.3.1.dist-info/WHEEL
the0_sdk-0.3.1.dist-info/top_level.txt
the0_sdk-0.3.1.dist-info/RECORD
