Metadata-Version: 2.4
Name: the0-sdk
Version: 0.3.1
Summary: SDK for building trading bots on the0 platform
Author-email: alexanderwanyoike <hello@the0.dev>
License: Apache-2.0
Project-URL: Homepage, https://the0.dev
Project-URL: Documentation, https://docs.the0.dev
Project-URL: Repository, https://github.com/alexanderwanyoike/the0
Project-URL: Source Code, https://github.com/alexanderwanyoike/the0/tree/main/sdk/python
Keywords: trading,bots,algorithmic-trading,the0,sdk
Classifier: Development Status :: 4 - Beta
Classifier: Intended Audience :: Developers
Classifier: License :: OSI Approved :: Apache Software License
Classifier: Programming Language :: Python :: 3
Classifier: Programming Language :: Python :: 3.9
Classifier: Programming Language :: Python :: 3.10
Classifier: Programming Language :: Python :: 3.11
Classifier: Programming Language :: Python :: 3.12
Classifier: Programming Language :: Python :: 3.13
Classifier: Topic :: Office/Business :: Financial :: Investment
Requires-Python: >=3.9
License-File: LICENSE
Dynamic: license-file
